setup.py
pyqm/__init__.py
pyqm/pyqm.py
pyqm.egg-info/PKG-INFO
pyqm.egg-info/SOURCES.txt
pyqm.egg-info/dependency_links.txt
pyqm.egg-info/requires.txt
pyqm.egg-info/top_level.txt