Metadata-Version: 1.1
Name: pyqm
Version: 0.0.4
Summary: Bulk queue management in MongoDB
Home-page: https://github.com/rh-marketingops/pyqm
Author: Jeremiah Coleman
Author-email: colemanja91@gmail.com
License: GNU General Public License
Keywords: queue management mongo mongodb bulk
Platform: any
Classifier: Programming Language :: Python
Classifier: Development Status :: 4 - Beta
Classifier: Natural Language :: English
Classifier: Environment :: Web Environment
Classifier: Intended Audience :: Developers
Classifier: License :: OSI Approved :: Apache Software License
Classifier: Operating System :: OS Independent
Classifier: Topic :: Software Development :: Libraries :: Python Modules
Classifier: Topic :: Software Development :: Libraries :: Application Frameworks
